<?xml version="1.0" encoding="gbk" ?>
<root	width="832"	height="226" >
	<table X="0" Y="0" width="1" height="1" isleaf="false" hdirection="true">
		<table X="0" Y="0" width="1" height="1" isleaf="true" hdirection="false" id="1" name="textpanel">																							
			<textpanel>
				<properties>
					<textcol title="Á×ËáÌúï®" fldname="TÁ×ËáÌúï®" titleclr="245,147,0"/>
					<textcol title="ÃÌËáï®" fldname="TÃÌËáï®" titleclr="245,147,0"/>
					<textcol title="îÜËáï®" fldname="TîÜËáï®" titleclr="245,147,0"/>
					<textcol title="ÈýÔª²ÄÁÏ" fldname="TÈýÔª²ÄÁÏ" titleclr="245,147,0"/>
				</properties>
				<datasource   reqformat="0"  name="cfg_hycyl_hyzt" body="82"></datasource>
			</textpanel>
		</table>
	</table>
</root>
